piecad/__init__.py
piecad/_color.py
piecad/_poly_point_isect.py
piecad/_text.py
piecad/bulk_ops.py
piecad/primitives_2d.py
piecad/primitives_3d.py
piecad/trigonometry.py
piecad/utilities.py
piecad/fonts/Hack-Regular-License.txt
piecad/fonts/Hack-Regular.ttf
piecad/fonts/Roboto-Regular-License.txt
piecad/fonts/Roboto-Regular.ttf
piecad/path/__init__.py
piecad/projectbox/__init__.py
piecad-1.0.8.dist-info/licenses/LICENSE
piecad-1.0.8.dist-info/WHEEL
piecad-1.0.8.dist-info/METADATA
piecad-1.0.8.dist-info/RECORD
