Metadata-Version: 2.4
Name: piecad
Version: 1.0.8
Summary: "Easy as Pie" CAD (Piecad)
Author-email: Brian Sturgill <codersnext@gmail.com>
Classifier: License :: OSI Approved :: MIT License
License-File: LICENSE
Requires-Dist: trimesh >= 1.26.4
Requires-Dist: fontPens >= 0.2.4
Requires-Dist: fontTools >= 4.57.0
Requires-Dist: manifold3d >= 3.0.1
Requires-Dist: skia-pathops >= 0.8.0
Requires-Dist: svgpathtools==1.7.0
Project-URL: Home, https://github.com/briansturgill/Piecad
